

[
{
	"datetime": "2024-12-15T15:55:17.000Z",
	"bird": {
	"name": "Helmeted Guineafowl",
	"family_name": "Guineafowl",
	"german_name": null,
	"afrikaans_name": null,
	"genus": "Numida",
	"species": "meleagris",
	"ebird": "https://ebird.org/species/helgui/ZA",
	"red-list": "least-concern",
	"photo": {
		"id": "2024-12-19T17:48:16.000Z_shaun",
		"tx": "-30%",
		"ty": "40%",
		"scale": 3
	}
},
	"quantity": "30-40",
	"location": {
		"areaId": "zevenwacht-wine-estate",
		"area": {
	"name": "Zevenwacht Wine Estate",
	"address": {
		"street": "Langverwacht Road",
		"suburb": "Kuils River"
	},
	"location": {
		"latitude": -33.931888,
		"longitude": 18.716808
	},
	"geofence": [
		[
			-33.9309527,
			18.7141857
		],
		[
			-33.9308127,
			18.7144212
		],
		[
			-33.9320831,
			18.717304
		],
		[
			-33.932684,
			18.7174435
		],
		[
			-33.9322052,
			18.7207401
		],
		[
			-33.9324722,
			18.7222636
		],
		[
			-33.9321874,
			18.7250531
		],
		[
			-33.9315725,
			18.7259023
		],
		[
			-33.9333885,
			18.7314169
		],
		[
			-33.9350798,
			18.7364809
		],
		[
			-33.9362545,
			18.7419818
		],
		[
			-33.9350834,
			18.7423465
		],
		[
			-33.9341359,
			18.7431834
		],
		[
			-33.9324268,
			18.743913
		],
		[
			-33.9326994,
			18.7396964
		],
		[
			-33.9297288,
			18.7334545
		],
		[
			-33.9220466,
			18.7333277
		],
		[
			-33.917565,
			18.7328871
		],
		[
			-33.9158734,
			18.7269434
		],
		[
			-33.9169632,
			18.7237554
		],
		[
			-33.9170522,
			18.7226396
		],
		[
			-33.9175864,
			18.7216955
		],
		[
			-33.9106511,
			18.7139467
		],
		[
			-33.9205235,
			18.7102106
		],
		[
			-33.9214022,
			18.7129427
		],
		[
			-33.9228381,
			18.7131359
		],
		[
			-33.9254008,
			18.7131009
		],
		[
			-33.9300981,
			18.7136009
		],
		[
			-33.9305521,
			18.713778
		],
		[
			-33.9309527,
			18.7141857
		]
	],
	"website": "https://zevenwacht.co.za/"
},
		"latitude": 
		
			-33.927155,
		
		"longitude":
		
			18.719967
		
	},
	
	"photos": {
		
			
			"2024-12-15T15:55:17.000Z_shaun":
			{
	"file": "A0E47C10-51D5-449C-94D0-CC6FBD5AD743_1_201_a.jpeg",
	"sighting": "2024-12-15T15:55:17.000Z_shaun",
	"description": "One of the larger groups of Guineafowl walking along the jeep track besides the vines, with several juveniles in tow.",
	"birds": [
		"guineafowl-helmeted"
	],
	"photographer": "shaun",
	"location": {
		"area": "zevenwacht-wine-estate",
		"latitude": -33.927155,
		"longitude": 18.719967
	}
}
		
	},
	
	"observers": [
		
			
			{
	"name": "Shaun",
	"full-name": "Shaun O'Connell",
	"email": "shaun@tactile.co.za"
}
		
			,
			{
	"name": "Ingunn",
	"full-name": "Ingunn O'Connell",
	"email": "groingunn@gmail.com"
}
		
	]
}
]